{
  "request": {
      "filter": {
          "map_id": "5",
          "mashupIDs": [],
          "customFields": []
      }
  },
  "markers": [
      {
          "map_id": "5",
          "address": "849 Maine Ave, Adrian, MN 56110, USA",
          "description": "",
          "pic": "",
          "link": "",
          "icon": {
              "url": "https:\/\/minnesotagolf.com\/wp-content\/plugins\/wp-google-maps\/images\/spotlight-poi2.png",
              "retina": false
          },
          "lat": "43.6252721",
          "lng": "-95.9332666",
          "anim": "0",
          "title": "Adrian Golf Course",
          "infoopen": "0",
          "category": "",
          "approved": "1",
          "retina": "0",
          "type": "0",
          "did": "",
          "sticky": "0",
          "other_data": "",
          "layergroup": "0",
          "id": "206",
          "categories": [],
          "custom_field_data": [],
          "rating": {
              "average": null,
              "count": "0"
          },
          "custom_fields_html": ""
      },
      {
          "map_id": "5",
          "address": "1202 28th Street Northeast, Austin, MN 55912, USA",
          "description": "",
          "pic": "",
          "link": "",
          "icon": {
              "url": "https:\/\/minnesotagolf.com\/wp-content\/plugins\/wp-google-maps\/images\/spotlight-poi2.png",
              "retina": false
          },
          "lat": "43.6777467",
          "lng": "-92.9240562",
          "anim": "0",
          "title": "Austin Country Club",
          "infoopen": "0",
          "category": "",
          "approved": "1",
          "retina": "0",
          "type": "0",
          "did": "",
          "sticky": "0",
          "other_data": "",
          "layergroup": "0",
          "id": "207",
          "categories": [],
          "custom_field_data": [],
          "rating": {
              "average": null,
              "count": "0"
          },
          "custom_fields_html": ""
      },
      {
          "map_id": "5",
          "address": "218 Hwy Ave N, Blooming Prairie, MN 55917, USA",
          "description": "",
          "pic": "",
          "link": "",
          "icon": {
              "url": "https:\/\/minnesotagolf.com\/wp-content\/plugins\/wp-google-maps\/images\/spotlight-poi2.png",
              "retina": false
          },
          "lat": "43.8682917",
          "lng": "-93.0504741",
          "anim": "0",
          "title": "Blooming Prairie Country Club",
          "infoopen": "0",
          "category": "",
          "approved": "1",
          "retina": "0",
          "type": "0",
          "did": "",
          "sticky": "0",
          "other_data": "",
          "layergroup": "0",
          "id": "208",
          "categories": [],
          "custom_field_data": [],
          "rating": {
              "average": null,
              "count": "0"
          },
          "custom_fields_html": ""
      },
      {
          "map_id": "5",
          "address": "14927 State Hwy 56, Adams, MN 55909, USA",
          "description": "",
          "pic": "",
          "link": "",
          "icon": {
              "url": "https:\/\/minnesotagolf.com\/wp-content\/plugins\/wp-google-maps\/images\/spotlight-poi2.png",
              "retina": false
          },
          "lat": "43.5696225",
          "lng": "-92.7538257",
          "anim": "0",
          "title": "Cedar River Golf Course",
          "infoopen": "0",
          "category": "",
          "approved": "1",
          "retina": "0",
          "type": "0",
          "did": "",
          "sticky": "0",
          "other_data": "",
          "layergroup": "0",
          "id": "209",
          "categories": [],
          "custom_field_data": [],
          "rating": {
              "average": null,
              "count": "0"
          },
          "custom_fields_html": ""
      },
      {
          "map_id": "5",
          "address": "County Road 9, Winona, MN, USA",
          "description": "",
          "pic": "",
          "link": "",
          "icon": {
              "url": "https:\/\/minnesotagolf.com\/wp-content\/plugins\/wp-google-maps\/images\/spotlight-poi2.png",
              "retina": false
          },
          "lat": "43.9675428",
          "lng": "-91.5492124",
          "anim": "0",
          "title": "Cedar Valley Golf Course",
          "infoopen": "0",
          "category": "",
          "approved": "1",
          "retina": "0",
          "type": "0",
          "did": "",
          "sticky": "0",
          "other_data": "",
          "layergroup": "0",
          "id": "210",
          "categories": [],
          "custom_field_data": [],
          "rating": {
              "average": null,
              "count": "0"
          },
          "custom_fields_html": ""
      },
      {
          "map_id": "5",
          "address": "1801 Main Street South, Chatfield, MN, USA",
          "description": "",
          "pic": "",
          "link": "",
          "icon": {
              "url": "https:\/\/minnesotagolf.com\/wp-content\/plugins\/wp-google-maps\/images\/spotlight-poi2.png",
              "retina": false
          },
          "lat": "43.8351206",
          "lng": "-92.1717723",
          "anim": "0",
          "title": "Chosen Valley Golf Club",
          "infoopen": "0",
          "category": "",
          "approved": "1",
          "retina": "0",
          "type": "0",
          "did": "",
          "sticky": "0",
          "other_data": "",
          "layergroup": "0",
          "id": "211",
          "categories": [],
          "custom_field_data": [],
          "rating": {
              "average": null,
              "count": "0"
          },
          "custom_fields_html": ""
      },
      {
          "map_id": "5",
          "address": "76785 270th St, Clarks Grove, MN 56016, USA",
          "description": "",
          "pic": "",
          "link": "",
          "icon": {
              "url": "https:\/\/minnesotagolf.com\/wp-content\/plugins\/wp-google-maps\/images\/spotlight-poi2.png",
              "retina": false
          },
          "lat": "43.7446584",
          "lng": "-93.33342189999999",
          "anim": "0",
          "title": "Clarks Grove Golf Course",
          "infoopen": "0",
          "category": "",
          "approved": "1",
          "retina": "0",
          "type": "0",
          "did": "",
          "sticky": "0",
          "other_data": "",
          "layergroup": "0",
          "id": "212",
          "categories": [],
          "custom_field_data": [],
          "rating": {
              "average": null,
              "count": "0"
          },
          "custom_fields_html": ""
      },
      {
          "map_id": "5",
          "address": "180 Coffee Mill Drive, Wabasha, MN 55981, USA",
          "description": "",
          "pic": "",
          "link": "",
          "icon": {
              "url": "https:\/\/minnesotagolf.com\/wp-content\/plugins\/wp-google-maps\/images\/spotlight-poi2.png",
              "retina": false
          },
          "lat": "44.3536593",
          "lng": "-92.0446948",
          "anim": "0",
          "title": "Coffee Mill Golf Course",
          "infoopen": "0",
          "category": "",
          "approved": "1",
          "retina": "0",
          "type": "0",
          "did": "",
          "sticky": "0",
          "other_data": "",
          "layergroup": "0",
          "id": "213",
          "categories": [],
          "custom_field_data": [],
          "rating": {
              "average": null,
              "count": "0"
          },
          "custom_fields_html": ""
      },
      {
          "map_id": "5",
          "address": "26826 Langford Ave, New Prague, MN 56071, USA",
          "description": "",
          "pic": "",
          "link": "",
          "icon": {
              "url": "https:\/\/minnesotagolf.com\/wp-content\/plugins\/wp-google-maps\/images\/spotlight-poi2.png",
              "retina": false
          },
          "lat": "44.5610717",
          "lng": "-93.50618899999999",
          "anim": "0",
          "title": "Creeksbend Golf Course",
          "infoopen": "0",
          "category": "",
          "approved": "1",
          "retina": "0",
          "type": "0",
          "did": "",
          "sticky": "0",
          "other_data": "",
          "layergroup": "0",
          "id": "214",
          "categories": [],
          "custom_field_data": [],
          "rating": {
              "average": null,
              "count": "0"
          },
          "custom_fields_html": ""
      },
      {
          "map_id": "5",
          "address": "18187 County Rd 34, Dodge Center, MN 55927, USA",
          "description": "",
          "pic": "",
          "link": "",
          "icon": {
              "url": "https:\/\/minnesotagolf.com\/wp-content\/plugins\/wp-google-maps\/images\/spotlight-poi2.png",
              "retina": false
          },
          "lat": "44.038705",
          "lng": "-92.8757782",
          "anim": "0",
          "title": "Dodge Country Club",
          "infoopen": "0",
          "category": "",
          "approved": "1",
          "retina": "0",
          "type": "0",
          "did": "",
          "sticky": "0",
          "other_data": "",
          "layergroup": "0",
          "id": "215",
          "categories": [],
          "custom_field_data": [],
          "rating": {
              "average": null,
              "count": "0"
          },
          "custom_fields_html": ""
      },
      {
          "map_id": "5",
          "address": "3505 Eastwood Rd SE, Rochester, MN 55904, USA",
          "description": "",
          "pic": "",
          "link": "",
          "icon": {
              "url": "https:\/\/minnesotagolf.com\/wp-content\/plugins\/wp-google-maps\/images\/spotlight-poi2.png",
              "retina": false
          },
          "lat": "44.0077981",
          "lng": "-92.4092542",
          "anim": "0",
          "title": "Eastwood Golf Club",
          "infoopen": "0",
          "category": "",
          "approved": "1",
          "retina": "0",
          "type": "0",
          "did": "",
          "sticky": "0",
          "other_data": "",
          "layergroup": "0",
          "id": "216",
          "categories": [],
          "custom_field_data": [],
          "rating": {
              "average": null,
              "count": "0"
          },
          "custom_fields_html": ""
      },
      {
          "map_id": "5",
          "address": "698 West Central Street, Sanborn, MN 56083, USA",
          "description": "",
          "pic": "",
          "link": "",
          "icon": {
              "url": "https:\/\/minnesotagolf.com\/wp-content\/plugins\/wp-google-maps\/images\/spotlight-poi2.png",
              "retina": false
          },
          "lat": "44.2168904",
          "lng": "-95.1335924",
          "anim": "0",
          "title": "Farmers Golf & Health Club",
          "infoopen": "0",
          "category": "",
          "approved": "1",
          "retina": "0",
          "type": "0",
          "did": "",
          "sticky": "0",
          "other_data": "",
          "layergroup": "0",
          "id": "217",
          "categories": [],
          "custom_field_data": [],
          "rating": {
              "average": null,
              "count": "0"
          },
          "custom_fields_html": ""
      },
      {
          "map_id": "5",
          "address": "23239 State Highway 16, Rushford, MN 55971, USA",
          "description": "",
          "pic": "",
          "link": "",
          "icon": {
              "url": "https:\/\/minnesotagolf.com\/wp-content\/plugins\/wp-google-maps\/images\/spotlight-poi2.png",
              "retina": false
          },
          "lat": "43.784379",
          "lng": "-91.7225066",
          "anim": "0",
          "title": "Ferndale Golf Course",
          "infoopen": "0",
          "category": "",
          "approved": "1",
          "retina": "0",
          "type": "0",
          "did": "",
          "sticky": "0",
          "other_data": "",
          "layergroup": "0",
          "id": "218",
          "categories": [],
          "custom_field_data": [],
          "rating": {
              "average": null,
              "count": "0"
          },
          "custom_fields_html": ""
      },
      {
          "map_id": "5",
          "address": "15 East Park Drive, Sherburn, MN 56171, USA",
          "description": "",
          "pic": "",
          "link": "",
          "icon": {
              "url": "https:\/\/minnesotagolf.com\/wp-content\/plugins\/wp-google-maps\/images\/spotlight-poi2.png",
              "retina": false
          },
          "lat": "43.6708452",
          "lng": "-94.7186943",
          "anim": "0",
          "title": "Fox Lake Golf Club",
          "infoopen": "0",
          "category": "",
          "approved": "1",
          "retina": "0",
          "type": "0",
          "did": "",
          "sticky": "0",
          "other_data": "",
          "layergroup": "0",
          "id": "219",
          "categories": [],
          "custom_field_data": [],
          "rating": {
              "average": null,
              "count": "0"
          },
          "custom_fields_html": ""
      },
      {
          "map_id": "5",
          "address": "101 Richway Dr, Albert Lea, MN 56007, USA",
          "description": "",
          "pic": "",
          "link": "",
          "icon": {
              "url": "https:\/\/minnesotagolf.com\/wp-content\/plugins\/wp-google-maps\/images\/spotlight-poi2.png",
              "retina": false
          },
          "lat": "43.6667237",
          "lng": "-93.36630009999999",
          "anim": "0",
          "title": "Green Lea Golf Course",
          "infoopen": "0",
          "category": "",
          "approved": "1",
          "retina": "0",
          "type": "0",
          "did": "",
          "sticky": "0",
          "other_data": "",
          "layergroup": "0",
          "id": "220",
          "categories": [],
          "custom_field_data": [],
          "rating": {
              "average": null,
              "count": "0"
          },
          "custom_fields_html": ""
      },
      {
          "map_id": "5",
          "address": "545 4th Street Northeast, Northeast Minneapolis, Minneapolis, MN, USA",
          "description": "",
          "pic": "",
          "link": "",
          "icon": {
              "url": "https:\/\/minnesotagolf.com\/wp-content\/plugins\/wp-google-maps\/images\/spotlight-poi2.png",
              "retina": false
          },
          "lat": "44.9948871",
          "lng": "-93.25894679999999",
          "anim": "0",
          "title": "Harmony Golf Club",
          "infoopen": "0",
          "category": "",
          "approved": "1",
          "retina": "0",
          "type": "0",
          "did": "",
          "sticky": "0",
          "other_data": "",
          "layergroup": "0",
          "id": "221",
          "categories": [],
          "custom_field_data": [],
          "rating": {
              "average": null,
              "count": "0"
          },
          "custom_fields_html": ""
      },
      {
          "map_id": "5",
          "address": "1035 North Shore Drive, Hendricks, MN 56136, USA",
          "description": "",
          "pic": "",
          "link": "",
          "icon": {
              "url": "https:\/\/minnesotagolf.com\/wp-content\/plugins\/wp-google-maps\/images\/spotlight-poi2.png",
              "retina": false
          },
          "lat": "44.5045646",
          "lng": "-96.4432442",
          "anim": "0",
          "title": "Hendricks Golf Club",
          "infoopen": "0",
          "category": "",
          "approved": "1",
          "retina": "0",
          "type": "0",
          "did": "",
          "sticky": "0",
          "other_data": "",
          "layergroup": "0",
          "id": "222",
          "categories": [],
          "custom_field_data": [],
          "rating": {
              "average": null,
              "count": "0"
          },
          "custom_fields_html": ""
      },
      {
          "map_id": "5",
          "address": "277 Amber Lake Drive, Fairmont, MN 56031, USA",
          "description": "",
          "pic": "",
          "link": "",
          "icon": {
              "url": "https:\/\/minnesotagolf.com\/wp-content\/plugins\/wp-google-maps\/images\/spotlight-poi2.png",
              "retina": false
          },
          "lat": "43.6084326",
          "lng": "-94.46764069999999",
          "anim": "0",
          "title": "Interlaken Golf Club",
          "infoopen": "0",
          "category": "",
          "approved": "1",
          "retina": "0",
          "type": "0",
          "did": "",
          "sticky": "0",
          "other_data": "",
          "layergroup": "0",
          "id": "223",
          "categories": [],
          "custom_field_data": [],
          "rating": {
              "average": null,
              "count": "0"
          },
          "custom_fields_html": ""
      },
      {
          "map_id": "5",
          "address": "71 N Hwy, Jackson, MN 56143, USA",
          "description": "",
          "pic": "",
          "link": "",
          "icon": {
              "url": "https:\/\/minnesotagolf.com\/wp-content\/plugins\/wp-google-maps\/images\/spotlight-poi2.png",
              "retina": false
          },
          "lat": "43.6237585",
          "lng": "-94.9874609",
          "anim": "0",
          "title": "Jackson Golf Club",
          "infoopen": "0",
          "category": "",
          "approved": "1",
          "retina": "0",
          "type": "0",
          "did": "",
          "sticky": "0",
          "other_data": "",
          "layergroup": "0",
          "id": "224",
          "categories": [],
          "custom_field_data": [],
          "rating": {
              "average": null,
              "count": "0"
          },
          "custom_fields_html": ""
      },
      {
          "map_id": "5",
          "address": "Minnesota 56, Kenyon, MN, USA",
          "description": "",
          "pic": "",
          "link": "",
          "icon": {
              "url": "https:\/\/minnesotagolf.com\/wp-content\/plugins\/wp-google-maps\/images\/spotlight-poi2.png",
              "retina": false
          },
          "lat": "44.2721724",
          "lng": "-92.9854094",
          "anim": "0",
          "title": "Kenyon Country Club",
          "infoopen": "0",
          "category": "",
          "approved": "1",
          "retina": "0",
          "type": "0",
          "did": "",
          "sticky": "0",
          "other_data": "",
          "layergroup": "0",
          "id": "225",
          "categories": [],
          "custom_field_data": [],
          "rating": {
              "average": null,
              "count": "0"
          },
          "custom_fields_html": ""
      },
      {
          "map_id": "5",
          "address": "Parkway Avenue South, Lanesboro, MN, USA",
          "description": "",
          "pic": "",
          "link": "",
          "icon": {
              "url": "https:\/\/minnesotagolf.com\/wp-content\/plugins\/wp-google-maps\/images\/spotlight-poi2.png",
              "retina": false
          },
          "lat": "43.7152393",
          "lng": "-91.97696069999999",
          "anim": "0",
          "title": "Lanesboro Golf Club",
          "infoopen": "0",
          "category": "",
          "approved": "1",
          "retina": "0",
          "type": "0",
          "did": "",
          "sticky": "0",
          "other_data": "",
          "layergroup": "0",
          "id": "226",
          "categories": [],
          "custom_field_data": [],
          "rating": {
              "average": null,
              "count": "0"
          },
          "custom_fields_html": ""
      },
      {
          "map_id": "5",
          "address": "311th Avenue, Le Sueur, MN, USA",
          "description": "",
          "pic": "",
          "link": "",
          "icon": {
              "url": "https:\/\/minnesotagolf.com\/wp-content\/plugins\/wp-google-maps\/images\/spotlight-poi2.png",
              "retina": false
          },
          "lat": "44.447078",
          "lng": "-93.8889153",
          "anim": "0",
          "title": "LeSueur Country Club",
          "infoopen": "0",
          "category": "",
          "approved": "1",
          "retina": "0",
          "type": "0",
          "did": "",
          "sticky": "0",
          "other_data": "",
          "layergroup": "0",
          "id": "227",
          "categories": [],
          "custom_field_data": [],
          "rating": {
              "average": null,
              "count": "0"
          },
          "custom_fields_html": ""
      },
      {
          "map_id": "5",
          "address": "19917 Co Hwy 14, Lewiston, MN 55952, USA",
          "description": "",
          "pic": "",
          "link": "",
          "icon": {
              "url": "https:\/\/minnesotagolf.com\/wp-content\/plugins\/wp-google-maps\/images\/spotlight-poi2.png",
              "retina": false
          },
          "lat": "43.9340106",
          "lng": "-91.88130220000001",
          "anim": "0",
          "title": "Lewiston Country Club",
          "infoopen": "0",
          "category": "",
          "approved": "1",
          "retina": "0",
          "type": "0",
          "did": "",
          "sticky": "0",
          "other_data": "",
          "layergroup": "0",
          "id": "228",
          "categories": [],
          "custom_field_data": [],
          "rating": {
              "average": null,
              "count": "0"
          },
          "custom_fields_html": ""
      },
      {
          "map_id": "5",
          "address": "73209 490th Ave, Jackson, MN 56143, USA",
          "description": "",
          "pic": "",
          "link": "",
          "icon": {
              "url": "https:\/\/minnesotagolf.com\/wp-content\/plugins\/wp-google-maps\/images\/spotlight-poi2.png",
              "retina": false
          },
          "lat": "43.549192",
          "lng": "-95.098446",
          "anim": "0",
          "title": "Loon Lake Golf Course",
          "infoopen": "0",
          "category": "",
          "approved": "1",
          "retina": "0",
          "type": "0",
          "did": "",
          "sticky": "0",
          "other_data": "",
          "layergroup": "0",
          "id": "229",
          "categories": [],
          "custom_field_data": [],
          "rating": {
              "average": null,
              "count": "0"
          },
          "custom_fields_html": ""
      },
      {
          "map_id": "5",
          "address": "1520 111th St, Luverne, MN 56156, USA",
          "description": "",
          "pic": "",
          "link": "",
          "icon": {
              "url": "https:\/\/minnesotagolf.com\/wp-content\/plugins\/wp-google-maps\/images\/spotlight-poi2.png",
              "retina": false
          },
          "lat": "43.6434214",
          "lng": "-96.1666753",
          "anim": "0",
          "title": "Luverne Country Club",
          "infoopen": "0",
          "category": "",
          "approved": "1",
          "retina": "0",
          "type": "0",
          "did": "",
          "sticky": "0",
          "other_data": "",
          "layergroup": "0",
          "id": "230",
          "categories": [],
          "custom_field_data": [],
          "rating": {
              "average": null,
              "count": "0"
          },
          "custom_fields_html": ""
      },
      {
          "map_id": "5",
          "address": "15939 State Highway 76, Caledonia, MN 55921, USA",
          "description": "",
          "pic": "",
          "link": "",
          "icon": {
              "url": "https:\/\/minnesotagolf.com\/wp-content\/plugins\/wp-google-maps\/images\/spotlight-poi2.png",
              "retina": false
          },
          "lat": "43.6172308",
          "lng": "-91.5066294",
          "anim": "0",
          "title": "Ma-Cal-Grove Country Club",
          "infoopen": "0",
          "category": "",
          "approved": "1",
          "retina": "0",
          "type": "0",
          "did": "",
          "sticky": "0",
          "other_data": "",
          "layergroup": "0",
          "id": "231",
          "categories": [],
          "custom_field_data": [],
          "rating": {
              "average": null,
              "count": "0"
          },
          "custom_fields_html": ""
      },
      {
          "map_id": "5",
          "address": "116 W Main St, Madelia, MN 56062, USA",
          "description": "",
          "pic": "",
          "link": "",
          "icon": {
              "url": "https:\/\/minnesotagolf.com\/wp-content\/plugins\/wp-google-maps\/images\/spotlight-poi2.png",
              "retina": false
          },
          "lat": "44.0506194",
          "lng": "-94.4188921",
          "anim": "0",
          "title": "Madelia Golf Course",
          "infoopen": "0",
          "category": "",
          "approved": "1",
          "retina": "0",
          "type": "0",
          "did": "",
          "sticky": "0",
          "other_data": "",
          "layergroup": "0",
          "id": "232",
          "categories": [],
          "custom_field_data": [],
          "rating": {
              "average": null,
              "count": "0"
          },
          "custom_fields_html": ""
      },
      {
          "map_id": "5",
          "address": "Country Club Drive, Mankato, MN, USA",
          "description": "",
          "pic": "",
          "link": "",
          "icon": {
              "url": "https:\/\/minnesotagolf.com\/wp-content\/plugins\/wp-google-maps\/images\/spotlight-poi2.png",
              "retina": false
          },
          "lat": "44.1924125",
          "lng": "-93.96414419999999",
          "anim": "0",
          "title": "Mankato Golf Club",
          "infoopen": "0",
          "category": "",
          "approved": "1",
          "retina": "0",
          "type": "0",
          "did": "",
          "sticky": "0",
          "other_data": "",
          "layergroup": "0",
          "id": "233",
          "categories": [],
          "custom_field_data": [],
          "rating": {
              "average": null,
              "count": "0"
          },
          "custom_fields_html": ""
      },
      {
          "map_id": "5",
          "address": "8600 Maple Valley Rd SE, Rochester, MN 55904, USA",
          "description": "",
          "pic": "",
          "link": "",
          "icon": {
              "url": "https:\/\/minnesotagolf.com\/wp-content\/plugins\/wp-google-maps\/images\/spotlight-poi2.png",
              "retina": false
          },
          "lat": "43.895938",
          "lng": "-92.37577999999999",
          "anim": "0",
          "title": "Maple Valley Golf & Country Club",
          "infoopen": "0",
          "category": "",
          "approved": "1",
          "retina": "0",
          "type": "0",
          "did": "",
          "sticky": "0",
          "other_data": "",
          "layergroup": "0",
          "id": "234",
          "categories": [],
          "custom_field_data": [],
          "rating": {
              "average": null,
              "count": "0"
          },
          "custom_fields_html": ""
      },
      {
          "map_id": "5",
          "address": "701 1st Street East, Stewartville, MN 55976, USA",
          "description": "",
          "pic": "",
          "link": "",
          "icon": {
              "url": "https:\/\/minnesotagolf.com\/wp-content\/plugins\/wp-google-maps\/images\/spotlight-poi2.png",
              "retina": false
          },
          "lat": "43.8555149",
          "lng": "-92.47705119999999",
          "anim": "0",
          "title": "Maple Brook Golf Course\t",
          "infoopen": "0",
          "category": "",
          "approved": "1",
          "retina": "0",
          "type": "0",
          "did": "",
          "sticky": "0",
          "other_data": "",
          "layergroup": "0",
          "id": "235",
          "categories": [],
          "custom_field_data": [],
          "rating": {
              "average": null,
              "count": "0"
          },
          "custom_fields_html": ""
      },
      {
          "map_id": "5",
          "address": "25238 540th Avenue, Austin, MN 55912, USA",
          "description": "",
          "pic": "",
          "link": "",
          "icon": {
              "url": "https:\/\/minnesotagolf.com\/wp-content\/plugins\/wp-google-maps\/images\/spotlight-poi2.png",
              "retina": false
          },
          "lat": "43.7210521",
          "lng": "-92.96917789999999",
          "anim": "0",
          "title": "Meadow Greens Golf Course",
          "infoopen": "0",
          "category": "",
          "approved": "1",
          "retina": "0",
          "type": "0",
          "did": "",
          "sticky": "0",
          "other_data": "",
          "layergroup": "0",
          "id": "236",
          "categories": [],
          "custom_field_data": [],
          "rating": {
              "average": null,
              "count": "0"
          },
          "custom_fields_html": ""
      },
      {
          "map_id": "5",
          "address": "410 Pintail Street, Mankato, MN 56001, USA",
          "description": "",
          "pic": "",
          "link": "",
          "icon": {
              "url": "https:\/\/minnesotagolf.com\/wp-content\/plugins\/wp-google-maps\/images\/spotlight-poi2.png",
              "retina": false
          },
          "lat": "44.1497585",
          "lng": "-94.0666808",
          "anim": "0",
          "title": "Minneopa Golf Club",
          "infoopen": "0",
          "category": "",
          "approved": "1",
          "retina": "0",
          "type": "0",
          "did": "",
          "sticky": "0",
          "other_data": "",
          "layergroup": "0",
          "id": "237",
          "categories": [],
          "custom_field_data": [],
          "rating": {
              "average": null,
              "count": "0"
          },
          "custom_fields_html": ""
      },
      {
          "map_id": "5",
          "address": "2346 U.S. 169, Elmore, MN, USA",
          "description": "",
          "pic": "",
          "link": "",
          "icon": {
              "url": "https:\/\/minnesotagolf.com\/wp-content\/plugins\/wp-google-maps\/images\/spotlight-poi2.png",
              "retina": false
          },
          "lat": "43.5202122",
          "lng": "-94.08605709999999",
          "anim": "0",
          "title": "Minn-Iowa Golf Course",
          "infoopen": "0",
          "category": "",
          "approved": "1",
          "retina": "0",
          "type": "0",
          "did": "",
          "sticky": "0",
          "other_data": "",
          "layergroup": "0",
          "id": "238",
          "categories": [],
          "custom_field_data": [],
          "rating": {
              "average": null,
              "count": "0"
          },
          "custom_fields_html": ""
      },
      {
          "map_id": "5",
          "address": "900 Rogers Drive, Montgomery, MN 56069, USA",
          "description": "",
          "pic": "",
          "link": "",
          "icon": {
              "url": "https:\/\/minnesotagolf.com\/wp-content\/plugins\/wp-google-maps\/images\/spotlight-poi2.png",
              "retina": false
          },
          "lat": "44.4491956",
          "lng": "-93.57709940000001",
          "anim": "0",
          "title": "Montgomery National Golf Club",
          "infoopen": "0",
          "category": "",
          "approved": "1",
          "retina": "0",
          "type": "0",
          "did": "",
          "sticky": "0",
          "other_data": "",
          "layergroup": "0",
          "id": "239",
          "categories": [],
          "custom_field_data": [],
          "rating": {
              "average": null,
              "count": "0"
          },
          "custom_fields_html": ""
      },
      {
          "map_id": "5",
          "address": "Golf Course Road, Mountain Lake, MN, USA",
          "description": "",
          "pic": "",
          "link": "",
          "icon": {
              "url": "https:\/\/minnesotagolf.com\/wp-content\/plugins\/wp-google-maps\/images\/spotlight-poi2.png",
              "retina": false
          },
          "lat": "43.9406819",
          "lng": "-94.93928179999999",
          "anim": "0",
          "title": "Mountain Lake Golf Course",
          "infoopen": "0",
          "category": "",
          "approved": "1",
          "retina": "0",
          "type": "0",
          "did": "",
          "sticky": "0",
          "other_data": "",
          "layergroup": "0",
          "id": "240",
          "categories": [],
          "custom_field_data": [],
          "rating": {
              "average": null,
              "count": "0"
          },
          "custom_fields_html": ""
      },
      {
          "map_id": "5",
          "address": "400 Lexington Avenue South, New Prague, MN 56071, USA",
          "description": "",
          "pic": "",
          "link": "",
          "icon": {
              "url": "https:\/\/minnesotagolf.com\/wp-content\/plugins\/wp-google-maps\/images\/spotlight-poi2.png",
              "retina": false
          },
          "lat": "44.5403116",
          "lng": "-93.56810229999999",
          "anim": "0",
          "title": "New Prague Golf Club",
          "infoopen": "0",
          "category": "",
          "approved": "1",
          "retina": "0",
          "type": "0",
          "did": "",
          "sticky": "0",
          "other_data": "",
          "layergroup": "0",
          "id": "241",
          "categories": [],
          "custom_field_data": [],
          "rating": {
              "average": null,
              "count": "0"
          },
          "custom_fields_html": ""
      },
      {
          "map_id": "5",
          "address": "1 Golf Drive, New Ulm, MN 56073, USA",
          "description": "",
          "pic": "",
          "link": "",
          "icon": {
              "url": "https:\/\/minnesotagolf.com\/wp-content\/plugins\/wp-google-maps\/images\/spotlight-poi2.png",
              "retina": false
          },
          "lat": "44.289183",
          "lng": "-94.4587665",
          "anim": "0",
          "title": "New Ulm Country Club",
          "infoopen": "0",
          "category": "",
          "approved": "1",
          "retina": "0",
          "type": "0",
          "did": "",
          "sticky": "0",
          "other_data": "",
          "layergroup": "0",
          "id": "242",
          "categories": [],
          "custom_field_data": [],
          "rating": {
              "average": null,
              "count": "0"
          },
          "custom_fields_html": ""
      },
      {
          "map_id": "5",
          "address": "41553 520th Street, North Mankato, MN 56003, USA",
          "description": "",
          "pic": "",
          "link": "",
          "icon": {
              "url": "https:\/\/minnesotagolf.com\/wp-content\/plugins\/wp-google-maps\/images\/spotlight-poi2.png",
              "retina": false
          },
          "lat": "44.1951236",
          "lng": "-94.100257",
          "anim": "0",
          "title": "North Links Golf Course",
          "infoopen": "0",
          "category": "",
          "approved": "1",
          "retina": "0",
          "type": "0",
          "did": "",
          "sticky": "0",
          "other_data": "",
          "layergroup": "0",
          "id": "243",
          "categories": [],
          "custom_field_data": [],
          "rating": {
              "average": null,
              "count": "0"
          },
          "custom_fields_html": ""
      },
      {
          "map_id": "5",
          "address": "4721 West Circle Drive, Rochester, MN 55901, USA",
          "description": "",
          "pic": "",
          "link": "",
          "icon": {
              "url": "https:\/\/minnesotagolf.com\/wp-content\/plugins\/wp-google-maps\/images\/spotlight-poi2.png",
              "retina": false
          },
          "lat": "44.0706978",
          "lng": "-92.5237887",
          "anim": "0",
          "title": "Northern Hills Golf Course",
          "infoopen": "0",
          "category": "",
          "approved": "1",
          "retina": "0",
          "type": "0",
          "did": "",
          "sticky": "0",
          "other_data": "",
          "layergroup": "0",
          "id": "244",
          "categories": [],
          "custom_field_data": [],
          "rating": {
              "average": null,
              "count": "0"
          },
          "custom_fields_html": ""
      },
      {
          "map_id": "5",
          "address": "2751 County Road 16 Southwest, Rochester, MN 55902, USA",
          "description": "",
          "pic": "",
          "link": "",
          "icon": {
              "url": "https:\/\/minnesotagolf.com\/wp-content\/plugins\/wp-google-maps\/images\/spotlight-poi2.png",
              "retina": false
          },
          "lat": "43.9203702",
          "lng": "-92.5029661",
          "anim": "0",
          "title": "Oak Summitt Golf Course",
          "infoopen": "0",
          "category": "",
          "approved": "1",
          "retina": "0",
          "type": "0",
          "did": "",
          "sticky": "0",
          "other_data": "",
          "layergroup": "0",
          "id": "245",
          "categories": [],
          "custom_field_data": [],
          "rating": {
              "average": null,
              "count": "0"
          },
          "custom_fields_html": ""
      },
      {
          "map_id": "5",
          "address": "170th Avenue, Hayfield, MN, USA",
          "description": "",
          "pic": "",
          "link": "",
          "icon": {
              "url": "https:\/\/minnesotagolf.com\/wp-content\/plugins\/wp-google-maps\/images\/spotlight-poi2.png",
              "retina": false
          },
          "lat": "43.93208449999999",
          "lng": "-92.8993047",
          "anim": "0",
          "title": "Oaks Golf Club",
          "infoopen": "0",
          "category": "",
          "approved": "1",
          "retina": "0",
          "type": "0",
          "did": "",
          "sticky": "0",
          "other_data": "",
          "layergroup": "0",
          "id": "246",
          "categories": [],
          "custom_field_data": [],
          "rating": {
              "average": null,
              "count": "0"
          },
          "custom_fields_html": ""
      },
      {
          "map_id": "5",
          "address": "920 8th St SE, Pine Island, MN 55963, USA",
          "description": "",
          "pic": "",
          "link": "",
          "icon": {
              "url": "https:\/\/minnesotagolf.com\/wp-content\/plugins\/wp-google-maps\/images\/spotlight-poi2.png",
              "retina": false
          },
          "lat": "44.1998441",
          "lng": "-92.6361811",
          "anim": "0",
          "title": "Pine Island Golf Course",
          "infoopen": "0",
          "category": "",
          "approved": "1",
          "retina": "0",
          "type": "0",
          "did": "",
          "sticky": "0",
          "other_data": "",
          "layergroup": "0",
          "id": "247",
          "categories": [],
          "custom_field_data": [],
          "rating": {
              "average": null,
              "count": "0"
          },
          "custom_fields_html": ""
      },
      {
          "map_id": "5",
          "address": "25233 534th St, Plainview, MN, USA",
          "description": "",
          "pic": "",
          "link": "",
          "icon": {
              "url": "https:\/\/minnesotagolf.com\/wp-content\/plugins\/wp-google-maps\/images\/spotlight-poi2.png",
              "retina": false
          },
          "lat": "44.153754",
          "lng": "-92.172184",
          "anim": "0",
          "title": "Piper Hills Golf Course",
          "infoopen": "0",
          "category": "",
          "approved": "1",
          "retina": "0",
          "type": "0",
          "did": "",
          "sticky": "0",
          "other_data": "",
          "layergroup": "0",
          "id": "248",
          "categories": [],
          "custom_field_data": [],
          "rating": {
              "average": null,
              "count": "0"
          },
          "custom_fields_html": ""
      },
      {
          "map_id": "5",
          "address": "921 8th Ave SE, Pipestone, MN 56164, USA",
          "description": "",
          "pic": "",
          "link": "",
          "icon": {
              "url": "https:\/\/minnesotagolf.com\/wp-content\/plugins\/wp-google-maps\/images\/spotlight-poi2.png",
              "retina": false
          },
          "lat": "43.99038780000001",
          "lng": "-96.3074719",
          "anim": "0",
          "title": "Pipestone Country Club",
          "infoopen": "0",
          "category": "",
          "approved": "1",
          "retina": "0",
          "type": "0",
          "did": "",
          "sticky": "0",
          "other_data": "",
          "layergroup": "0",
          "id": "249",
          "categories": [],
          "custom_field_data": [],
          "rating": {
              "average": null,
              "count": "0"
          },
          "custom_fields_html": ""
      },
      {
          "map_id": "5",
          "address": "2000 North Main Street, Janesville, MN 56048, USA",
          "description": "",
          "pic": "",
          "link": "",
          "icon": {
              "url": "https:\/\/minnesotagolf.com\/wp-content\/plugins\/wp-google-maps\/images\/spotlight-poi2.png",
              "retina": false
          },
          "lat": "44.1276579",
          "lng": "-93.70928280000001",
          "anim": "0",
          "title": "Prairie Ridge Golf Course",
          "infoopen": "0",
          "category": "",
          "approved": "1",
          "retina": "0",
          "type": "0",
          "did": "",
          "sticky": "0",
          "other_data": "",
          "layergroup": "0",
          "id": "250",
          "categories": [],
          "custom_field_data": [],
          "rating": {
              "average": null,
              "count": "0"
          },
          "custom_fields_html": ""
      },
      {
          "map_id": "5",
          "address": "30784 State Highway 266, Worthington, MN 56187, USA",
          "description": "",
          "pic": "",
          "link": "",
          "icon": {
              "url": "https:\/\/minnesotagolf.com\/wp-content\/plugins\/wp-google-maps\/images\/spotlight-poi2.png",
              "retina": false
          },
          "lat": "43.6402012",
          "lng": "-95.6272321",
          "anim": "0",
          "title": "Prairie View Golf Club",
          "infoopen": "0",
          "category": "",
          "approved": "1",
          "retina": "0",
          "type": "0",
          "did": "",
          "sticky": "0",
          "other_data": "",
          "layergroup": "0",
          "id": "251",
          "categories": [],
          "custom_field_data": [],
          "rating": {
              "average": null,
              "count": "0"
          },
          "custom_fields_html": ""
      },
      {
          "map_id": "5",
          "address": "State Hwy 16, Preston, MN 55965, USA",
          "description": "",
          "pic": "",
          "link": "",
          "icon": {
              "url": "https:\/\/minnesotagolf.com\/wp-content\/plugins\/wp-google-maps\/images\/spotlight-poi2.png",
              "retina": false
          },
          "lat": "43.67541689999999",
          "lng": "-92.0836479",
          "anim": "0",
          "title": "Preston Golf & Country Club",
          "infoopen": "0",
          "category": "",
          "approved": "1",
          "retina": "0",
          "type": "0",
          "did": "",
          "sticky": "0",
          "other_data": "",
          "layergroup": "0",
          "id": "252",
          "categories": [],
          "custom_field_data": [],
          "rating": {
              "average": null,
              "count": "0"
          },
          "custom_fields_html": ""
      },
      {
          "map_id": "5",
          "address": "36259 150th Street, Blue Earth, MN 56013, USA",
          "description": "",
          "pic": "",
          "link": "",
          "icon": {
              "url": "https:\/\/minnesotagolf.com\/wp-content\/plugins\/wp-google-maps\/images\/spotlight-poi2.png",
              "retina": false
          },
          "lat": "43.7085915",
          "lng": "-94.1432954",
          "anim": "0",
          "title": "Riverside Town & Country Club",
          "infoopen": "0",
          "category": "",
          "approved": "1",
          "retina": "0",
          "type": "0",
          "did": "",
          "sticky": "0",
          "other_data": "",
          "layergroup": "0",
          "id": "253",
          "categories": [],
          "custom_field_data": [],
          "rating": {
              "average": null,
              "count": "0"
          },
          "custom_fields_html": ""
      },
      {
          "map_id": "5",
          "address": "1800 Clubhouse Dr NE, Stewartville, MN 55976, USA",
          "description": "",
          "pic": "",
          "link": "",
          "icon": {
              "url": "https:\/\/minnesotagolf.com\/wp-content\/plugins\/wp-google-maps\/images\/spotlight-poi2.png",
              "retina": false
          },
          "lat": "43.8664693",
          "lng": "-92.48305909999999",
          "anim": "0",
          "title": "Riverview Greens",
          "infoopen": "0",
          "category": "",
          "approved": "1",
          "retina": "0",
          "type": "0",
          "did": "",
          "sticky": "0",
          "other_data": "",
          "layergroup": "0",
          "id": "254",
          "categories": [],
          "custom_field_data": [],
          "rating": {
              "average": null,
              "count": "0"
          },
          "custom_fields_html": ""
      },
      {
          "map_id": "5",
          "address": "3100 Country Club Road Southwest, Rochester, MN, USA",
          "description": "",
          "pic": "",
          "link": "",
          "icon": {
              "url": "https:\/\/minnesotagolf.com\/wp-content\/plugins\/wp-google-maps\/images\/spotlight-poi2.png",
              "retina": false
          },
          "lat": "44.0222811",
          "lng": "-92.5120712",
          "anim": "0",
          "title": "Rochester Golf & Country Club",
          "infoopen": "0",
          "category": "",
          "approved": "1",
          "retina": "0",
          "type": "0",
          "did": "",
          "sticky": "0",
          "other_data": "",
          "layergroup": "0",
          "id": "255",
          "categories": [],
          "custom_field_data": [],
          "rating": {
              "average": null,
              "count": "0"
          },
          "custom_fields_html": ""
      },
      {
          "map_id": "5",
          "address": "1360 280th Ave, Westbrook, MN 56183, USA",
          "description": "",
          "pic": "",
          "link": "",
          "icon": {
              "url": "https:\/\/minnesotagolf.com\/wp-content\/plugins\/wp-google-maps\/images\/spotlight-poi2.png",
              "retina": false
          },
          "lat": "44.0472334",
          "lng": "-95.4999639",
          "anim": "0",
          "title": "Rolling Hills Golf Club",
          "infoopen": "0",
          "category": "",
          "approved": "1",
          "retina": "0",
          "type": "0",
          "did": "",
          "sticky": "0",
          "other_data": "",
          "layergroup": "0",
          "id": "256",
          "categories": [],
          "custom_field_data": [],
          "rating": {
              "average": null,
              "count": "0"
          },
          "custom_fields_html": ""
      },
      {
          "map_id": "5",
          "address": "2456 104th St, Fairmont, MN 56031, USA",
          "description": "",
          "pic": "",
          "link": "",
          "icon": {
              "url": "https:\/\/minnesotagolf.com\/wp-content\/plugins\/wp-google-maps\/images\/spotlight-poi2.png",
              "retina": false
          },
          "lat": "43.6327886",
          "lng": "-94.3788433",
          "anim": "0",
          "title": "Rose Lake Golf Club",
          "infoopen": "0",
          "category": "",
          "approved": "1",
          "retina": "0",
          "type": "0",
          "did": "",
          "sticky": "0",
          "other_data": "",
          "layergroup": "0",
          "id": "257",
          "categories": [],
          "custom_field_data": [],
          "rating": {
              "average": null,
              "count": "0"
          },
          "custom_fields_html": ""
      },
      {
          "map_id": "5",
          "address": "Lake Emily Road, St Peter, MN 56082, USA",
          "description": "",
          "pic": "",
          "link": "",
          "icon": {
              "url": "https:\/\/minnesotagolf.com\/wp-content\/plugins\/wp-google-maps\/images\/spotlight-poi2.png",
              "retina": false
          },
          "lat": "44.3047587",
          "lng": "-93.9208116",
          "anim": "0",
          "title": "Shoreland Country Club",
          "infoopen": "0",
          "category": "",
          "approved": "1",
          "retina": "0",
          "type": "0",
          "did": "",
          "sticky": "0",
          "other_data": "",
          "layergroup": "0",
          "id": "258",
          "categories": [],
          "custom_field_data": [],
          "rating": {
              "average": null,
              "count": "0"
          },
          "custom_fields_html": ""
      },
      {
          "map_id": "5",
          "address": "Slayton, MN 56172, USA",
          "description": "",
          "pic": "",
          "link": "",
          "icon": {
              "url": "https:\/\/minnesotagolf.com\/wp-content\/plugins\/wp-google-maps\/images\/spotlight-poi2.png",
              "retina": false
          },
          "lat": "43.9877419",
          "lng": "-95.7558464",
          "anim": "0",
          "title": "Slayton Country Club",
          "infoopen": "0",
          "category": "",
          "approved": "1",
          "retina": "0",
          "type": "0",
          "did": "",
          "sticky": "0",
          "other_data": "",
          "layergroup": "0",
          "id": "259",
          "categories": [],
          "custom_field_data": [],
          "rating": {
              "average": null,
              "count": "0"
          },
          "custom_fields_html": ""
      },
      {
          "map_id": "5",
          "address": "27898 U.S. 14, Sleepy Eye, MN 56085, USA",
          "description": "",
          "pic": "",
          "link": "",
          "icon": {
              "url": "https:\/\/minnesotagolf.com\/wp-content\/plugins\/wp-google-maps\/images\/spotlight-poi2.png",
              "retina": false
          },
          "lat": "44.294101",
          "lng": "-94.75052699999999",
          "anim": "0",
          "title": "Sleepy Eye Golf Club",
          "infoopen": "0",
          "category": "",
          "approved": "1",
          "retina": "0",
          "type": "0",
          "did": "",
          "sticky": "0",
          "other_data": "",
          "layergroup": "0",
          "id": "260",
          "categories": [],
          "custom_field_data": [],
          "rating": {
              "average": null,
              "count": "0"
          },
          "custom_fields_html": ""
      },
      {
          "map_id": "5",
          "address": "244 Soldiers Field Dr SE, Rochester, MN 55902, USA",
          "description": "",
          "pic": "",
          "link": "",
          "icon": {
              "url": "https:\/\/minnesotagolf.com\/wp-content\/plugins\/wp-google-maps\/images\/spotlight-poi2.png",
              "retina": false
          },
          "lat": "44.0108517",
          "lng": "-92.4660214",
          "anim": "0",
          "title": "Soldiers Memorial Field Golf Course",
          "infoopen": "0",
          "category": "",
          "approved": "1",
          "retina": "0",
          "type": "0",
          "did": "",
          "sticky": "0",
          "other_data": "",
          "layergroup": "0",
          "id": "261",
          "categories": [],
          "custom_field_data": [],
          "rating": {
              "average": null,
              "count": "0"
          },
          "custom_fields_html": ""
      },
      {
          "map_id": "5",
          "address": "975 Somerby Parkway Northeast, Byron, MN 55920, USA",
          "description": "",
          "pic": "",
          "link": "",
          "icon": {
              "url": "https:\/\/minnesotagolf.com\/wp-content\/plugins\/wp-google-maps\/images\/spotlight-poi2.png",
              "retina": false
          },
          "lat": "44.0479109",
          "lng": "-92.63505649999999",
          "anim": "0",
          "title": "Somerby Golf Club",
          "infoopen": "0",
          "category": "",
          "approved": "1",
          "retina": "0",
          "type": "0",
          "did": "",
          "sticky": "0",
          "other_data": "",
          "layergroup": "0",
          "id": "262",
          "categories": [],
          "custom_field_data": [],
          "rating": {
              "average": null,
              "count": "0"
          },
          "custom_fields_html": ""
      },
      {
          "map_id": "5",
          "address": "1920 Gladiola Drive, St Charles, MN 55972, USA",
          "description": "",
          "pic": "",
          "link": "",
          "icon": {
              "url": "https:\/\/minnesotagolf.com\/wp-content\/plugins\/wp-google-maps\/images\/spotlight-poi2.png",
              "retina": false
          },
          "lat": "43.9589858",
          "lng": "-92.0478794",
          "anim": "0",
          "title": "St. Charles Golf Course",
          "infoopen": "0",
          "category": "",
          "approved": "1",
          "retina": "0",
          "type": "0",
          "did": "",
          "sticky": "0",
          "other_data": "",
          "layergroup": "0",
          "id": "263",
          "categories": [],
          "custom_field_data": [],
          "rating": {
              "average": null,
              "count": "0"
          },
          "custom_fields_html": ""
      },
      {
          "map_id": "5",
          "address": "State Hwy 22, Litchfield, MN, USA",
          "description": "",
          "pic": "",
          "link": "",
          "icon": {
              "url": "https:\/\/minnesotagolf.com\/wp-content\/plugins\/wp-google-maps\/images\/spotlight-poi2.png",
              "retina": false
          },
          "lat": "45.125844",
          "lng": "-94.5282046",
          "anim": "0",
          "title": "Terrace View Golf Course",
          "infoopen": "0",
          "category": "",
          "approved": "1",
          "retina": "0",
          "type": "0",
          "did": "",
          "sticky": "0",
          "other_data": "",
          "layergroup": "0",
          "id": "264",
          "categories": [],
          "custom_field_data": [],
          "rating": {
              "average": null,
              "count": "0"
          },
          "custom_fields_html": ""
      },
      {
          "map_id": "5",
          "address": "22852 County Road 17, Winona, MN 55987, USA",
          "description": "",
          "pic": "",
          "link": "",
          "icon": {
              "url": "https:\/\/minnesotagolf.com\/wp-content\/plugins\/wp-google-maps\/images\/spotlight-poi2.png",
              "retina": false
          },
          "lat": "44.0074668",
          "lng": "-91.60558449999999",
          "anim": "0",
          "title": "The Bridges Golf Course",
          "infoopen": "0",
          "category": "",
          "approved": "1",
          "retina": "0",
          "type": "0",
          "did": "",
          "sticky": "0",
          "other_data": "",
          "layergroup": "0",
          "id": "265",
          "categories": [],
          "custom_field_data": [],
          "rating": {
              "average": null,
              "count": "0"
          },
          "custom_fields_html": ""
      },
      {
          "map_id": "5",
          "address": "9203 Mound Prairie Drive, Houston, MN 55943, USA",
          "description": "",
          "pic": "",
          "link": "",
          "icon": {
              "url": "https:\/\/minnesotagolf.com\/wp-content\/plugins\/wp-google-maps\/images\/spotlight-poi2.png",
              "retina": false
          },
          "lat": "43.7575165",
          "lng": "-91.4292284",
          "anim": "0",
          "title": "Valley High Golf Club",
          "infoopen": "0",
          "category": "",
          "approved": "1",
          "retina": "0",
          "type": "0",
          "did": "",
          "sticky": "0",
          "other_data": "",
          "layergroup": "0",
          "id": "266",
          "categories": [],
          "custom_field_data": [],
          "rating": {
              "average": null,
              "count": "0"
          },
          "custom_fields_html": ""
      },
      {
          "map_id": "5",
          "address": "37160 Clear Lake Drive, Waseca, MN 56093, USA",
          "description": "",
          "pic": "",
          "link": "",
          "icon": {
              "url": "https:\/\/minnesotagolf.com\/wp-content\/plugins\/wp-google-maps\/images\/spotlight-poi2.png",
              "retina": false
          },
          "lat": "44.09894999999999",
          "lng": "-93.4814648",
          "anim": "0",
          "title": "Waseca Lakeside Club",
          "infoopen": "0",
          "category": "",
          "approved": "1",
          "retina": "0",
          "type": "0",
          "did": "",
          "sticky": "0",
          "other_data": "",
          "layergroup": "0",
          "id": "267",
          "categories": [],
          "custom_field_data": [],
          "rating": {
              "average": null,
              "count": "0"
          },
          "custom_fields_html": ""
      },
      {
          "map_id": "5",
          "address": "1st Avenue Southwest, Wells, MN, USA",
          "description": "",
          "pic": "",
          "link": "",
          "icon": {
              "url": "https:\/\/minnesotagolf.com\/wp-content\/plugins\/wp-google-maps\/images\/spotlight-poi2.png",
              "retina": false
          },
          "lat": "43.7410101",
          "lng": "-93.7268886",
          "anim": "0",
          "title": "Wells Golf Club",
          "infoopen": "0",
          "category": "",
          "approved": "1",
          "retina": "0",
          "type": "0",
          "did": "",
          "sticky": "0",
          "other_data": "",
          "layergroup": "0",
          "id": "268",
          "categories": [],
          "custom_field_data": [],
          "rating": {
              "average": null,
              "count": "0"
          },
          "custom_fields_html": ""
      },
      {
          "map_id": "5",
          "address": "1460 West 5th Street, Winona, MN, USA",
          "description": "",
          "pic": "",
          "link": "",
          "icon": {
              "url": "https:\/\/minnesotagolf.com\/wp-content\/plugins\/wp-google-maps\/images\/spotlight-poi2.png",
              "retina": false
          },
          "lat": "44.0545769",
          "lng": "-91.6762969",
          "anim": "0",
          "title": "Westfield Golf Club",
          "infoopen": "0",
          "category": "",
          "approved": "1",
          "retina": "0",
          "type": "0",
          "did": "",
          "sticky": "0",
          "other_data": "",
          "layergroup": "0",
          "id": "269",
          "categories": [],
          "custom_field_data": [],
          "rating": {
              "average": null,
              "count": "0"
          },
          "custom_fields_html": ""
      },
      {
          "map_id": "5",
          "address": "1700 48th Street Southwest, Rochester, MN 55902, USA",
          "description": "",
          "pic": "",
          "link": "",
          "icon": {
              "url": "https:\/\/minnesotagolf.com\/wp-content\/plugins\/wp-google-maps\/images\/spotlight-poi2.png",
              "retina": false
          },
          "lat": "43.9512399",
          "lng": "-92.48619",
          "anim": "0",
          "title": "Willow Creek Golf Course",
          "infoopen": "0",
          "category": "",
          "approved": "1",
          "retina": "0",
          "type": "0",
          "did": "",
          "sticky": "0",
          "other_data": "",
          "layergroup": "0",
          "id": "270",
          "categories": [],
          "custom_field_data": [],
          "rating": {
              "average": null,
              "count": "0"
          },
          "custom_fields_html": ""
      },
      {
          "map_id": "5",
          "address": "Country Club Drive, Windom, MN, USA",
          "description": "",
          "pic": "",
          "link": "",
          "icon": {
              "url": "https:\/\/minnesotagolf.com\/wp-content\/plugins\/wp-google-maps\/images\/spotlight-poi2.png",
              "retina": false
          },
          "lat": "43.8912104",
          "lng": "-95.1401587",
          "anim": "0",
          "title": "Windom Country Club",
          "infoopen": "0",
          "category": "",
          "approved": "1",
          "retina": "0",
          "type": "0",
          "did": "",
          "sticky": "0",
          "other_data": "",
          "layergroup": "0",
          "id": "271",
          "categories": [],
          "custom_field_data": [],
          "rating": {
              "average": null,
              "count": "0"
          },
          "custom_fields_html": ""
      },
      {
          "map_id": "5",
          "address": "851 West Oxford Street, Worthington, MN 56187, USA",
          "description": "",
          "pic": "",
          "link": "",
          "icon": {
              "url": "https:\/\/minnesotagolf.com\/wp-content\/plugins\/wp-google-maps\/images\/spotlight-poi2.png",
              "retina": false
          },
          "lat": "43.62910960000001",
          "lng": "-95.6221801",
          "anim": "0",
          "title": "Worthington Country Club",
          "infoopen": "0",
          "category": "",
          "approved": "1",
          "retina": "0",
          "type": "0",
          "did": "",
          "sticky": "0",
          "other_data": "",
          "layergroup": "0",
          "id": "272",
          "categories": [],
          "custom_field_data": [],
          "rating": {
              "average": null,
              "count": "0"
          },
          "custom_fields_html": ""
      },
      {
          "map_id": "5",
          "address": "60146 US Hwy 63, Zumbro Falls, MN 55991, USA",
          "description": "",
          "pic": "",
          "link": "",
          "icon": {
              "url": "https:\/\/minnesotagolf.com\/wp-content\/plugins\/wp-google-maps\/images\/spotlight-poi2.png",
              "retina": false
          },
          "lat": "44.2537522",
          "lng": "-92.4298196",
          "anim": "0",
          "title": "Zumbro Falls Golf Club",
          "infoopen": "0",
          "category": "",
          "approved": "1",
          "retina": "0",
          "type": "0",
          "did": "",
          "sticky": "0",
          "other_data": "",
          "layergroup": "0",
          "id": "273",
          "categories": [],
          "custom_field_data": [],
          "rating": {
              "average": null,
              "count": "0"
          },
          "custom_fields_html": ""
      },
      {
          "map_id": "5",
          "address": "25202 615th Street, Mantorville, MN, USA",
          "description": "",
          "pic": "",
          "link": "",
          "icon": {
              "url": "https:\/\/minnesotagolf.com\/wp-content\/plugins\/wp-google-maps\/images\/spotlight-poi2.png",
              "retina": false
          },
          "lat": "44.060477",
          "lng": "-92.731955",
          "anim": "0",
          "title": "Zumbro Valley Golf Course",
          "infoopen": "0",
          "category": "",
          "approved": "1",
          "retina": "0",
          "type": "0",
          "did": "",
          "sticky": "0",
          "other_data": "",
          "layergroup": "0",
          "id": "274",
          "categories": [],
          "custom_field_data": [],
          "rating": {
              "average": null,
              "count": "0"
          },
          "custom_fields_html": ""
      },
      {
          "map_id": "5",
          "address": "80 Golf Links Ave, Zumbrota, MN 55992, USA",
          "description": "",
          "pic": "",
          "link": "",
          "icon": {
              "url": "https:\/\/minnesotagolf.com\/wp-content\/plugins\/wp-google-maps\/images\/spotlight-poi2.png",
              "retina": false
          },
          "lat": "44.3093557",
          "lng": "-92.6750091",
          "anim": "0",
          "title": "Zumbrota Golf Club",
          "infoopen": "0",
          "category": "",
          "approved": "1",
          "retina": "0",
          "type": "0",
          "did": "",
          "sticky": "0",
          "other_data": "",
          "layergroup": "0",
          "id": "275",
          "categories": [],
          "custom_field_data": [],
          "rating": {
              "average": null,
              "count": "0"
          },
          "custom_fields_html": ""
      }
  ],
  "circles": [],
  "pointlabels": [],
  "polygons": [],
  "polylines": [],
  "rectangles": [],
  "heatmaps": []
}